zope.ptresource-5.0-py3.9-nspkg.pth
zope/ptresource/__init__.py
zope/ptresource/configure.zcml
zope/ptresource/ptresource.py
zope/ptresource/tests.py
zope.ptresource-5.0.dist-info/LICENSE.txt
zope.ptresource-5.0.dist-info/METADATA
zope.ptresource-5.0.dist-info/WHEEL
zope.ptresource-5.0.dist-info/namespace_packages.txt
zope.ptresource-5.0.dist-info/top_level.txt
zope.ptresource-5.0.dist-info/RECORD
