Metadata-Version: 2.1
Name: zope.ptresource
Version: 5.0
Summary: Page template resource plugin for zope.browserresource
Home-page: https://github.com/zopefoundation/zope.ptresource/
Author: Zope Foundation and Contributors
Author-email: zope-dev@zope.dev
License: ZPL 2.1
Project-URL: Issue Tracker, https://github.com/zopefoundation/zope.ptresource/issues
Project-URL: Sources, https://github.com/zopefoundation/zope.ptresource
Classifier: Environment :: Web Environment
Classifier: Intended Audience :: Developers
Classifier: License :: OSI Approved :: Zope Public License
Classifier: Programming Language :: Python
Classifier: Programming Language :: Python :: 3
Classifier: Programming Language :: Python :: 3.7
Classifier: Programming Language :: Python :: 3.8
Classifier: Programming Language :: Python :: 3.9
Classifier: Programming Language :: Python :: 3.10
Classifier: Programming Language :: Python :: 3.11
Classifier: Programming Language :: Python :: Implementation :: CPython
Classifier: Programming Language :: Python :: Implementation :: PyPy
Classifier: Operating System :: OS Independent
Classifier: Topic :: Internet :: WWW/HTTP
Classifier: Framework :: Zope :: 3
Requires-Python: >=3.7
Provides-Extra: test
License-File: LICENSE.txt
